LICENSE
MANIFEST.in
README.md
requirements.txt
setup.py
/opt/miniconda3/lib/python3.7/site-packages/numpy/core/include/numpy/arrayobject.h
/opt/miniconda3/lib/python3.7/site-packages/numpy/core/include/numpy/ufuncobject.h
examples/decompose_fmri.py
examples/decompose_images.py
examples/predict_recsys.py
misc/download.sh
misc/matplotlibrc
modl/__init__.py
modl/setup.py
modl.egg-info/PKG-INFO
modl.egg-info/SOURCES.txt
modl.egg-info/dependency_links.txt
modl.egg-info/not-zip-safe
modl.egg-info/top_level.txt
modl/datasets/__init__.py
modl/datasets/adhd.py
modl/datasets/image.py
modl/datasets/images_fast.c
modl/datasets/recsys.py
modl/datasets/setup.py
modl/datasets/tests/__init__.py
modl/datasets/tests/test_adhd.py
modl/decomposition/__init__.py
modl/decomposition/dict_fact.py
modl/decomposition/dict_fact_fast.c
modl/decomposition/dict_fact_fast.pyx
modl/decomposition/fmri.py
modl/decomposition/image.py
modl/decomposition/recsys.py
modl/decomposition/recsys_fast.c
modl/decomposition/recsys_fast.pyx
modl/decomposition/setup.py
modl/decomposition/tests/__init__.py
modl/decomposition/tests/test_dict_fact.py
modl/decomposition/tests/test_fmri.py
modl/decomposition/tests/test_recsys.py
modl/feature_extraction/__init__.py
modl/feature_extraction/image.py
modl/feature_extraction/setup.py
modl/feature_extraction/tests/__init__.py
modl/input_data/__init__.py
modl/input_data/image.py
modl/input_data/image_fast.c
modl/input_data/image_fast.pyx
modl/input_data/setup.py
modl/input_data/fmri/__init__.py
modl/input_data/fmri/base.py
modl/input_data/fmri/fixes.py
modl/input_data/fmri/rest.py
modl/input_data/fmri/unmask.py
modl/input_data/tests/__init__.py
modl/input_data/tests/test_image.py
modl/plotting/__init__.py
modl/plotting/fmri.py
modl/plotting/image.py
modl/plotting/setup.py
modl/plotting/tests/__init__.py
modl/utils/__init__.py
modl/utils/setup.py
modl/utils/system.py
modl/utils/math/__init__.py
modl/utils/math/enet.c
modl/utils/math/enet.pxd
modl/utils/math/enet.pyx
modl/utils/math/enet_proj.c
modl/utils/math/setup.py
modl/utils/math/tests/__init__.py
modl/utils/math/tests/test_enet.py
