Metadata-Version: 1.2
Name: modl
Version: 0.6.1.1
Summary: Subsampled Online Matrix Factorization in Python
Home-page: https://github.com/arthurmensch/modl
Maintainer: Arthur Mensch
Maintainer-email: arthur.mensch@m4x.org
License: new BSD
Download-URL: https://github.com/arthurmensch/modl
Platform: UNKNOWN
Classifier: Intended Audience :: Science/Research
Classifier: Intended Audience :: Developers
Classifier: License :: OSI Approved
Classifier: Programming Language :: C
Classifier: Programming Language :: Python
Classifier: Topic :: Software Development
Classifier: Topic :: Scientific/Engineering
Classifier: Operating System :: Microsoft :: Windows
Classifier: Operating System :: POSIX
Classifier: Operating System :: Unix
Classifier: Operating System :: MacOS
Classifier: Programming Language :: Python :: 3.5
